{
    "lineEdit2_1": "1",
    "lineEdit2_2": "1",
    "lineEdit2_3": "1",
    "lineEdit2_4": "1",
    "lineEdit2_5": "1",
    "lineEdit2_6": "1",
    "lineEdit2_7": "1",
    "lineEdit2_8": "1",
    "lineEdit2_9": "1",
    "lineEdit2_10": "11",
    "lineEdit2_11": "11",
    "lineEdit2_12": "11",
    "lineEdit2_13": "11",
    "lineEdit2_14": "1",
    "lineEdit2_15": "1",
    "lineEdit2_16": "11",
    "lineEdit2_17": "11",
    "lineEdit2_18": "1",
    "lineEdit2_19": "1",
    "lineEdit2_20": "1",
    "lineEdit_1": "1",
    "lineEdit_2": "1",
    "lineEdit_3": "1",
    "lineEdit_4": "1",
    "lineEdit_5": "1",
    "lineEdit_6": "1",
    "lineEdit_7": "1",
    "lineEdit_8": "1",
    "lineEdit_9": "11",
    "lineEdit_10": "11",
    "lineEdit_11": "11",
    "lineEdit_12": "11",
    "lineEdit_13": "1",
    "lineEdit_14": "1",
    "lineEdit_15": "11",
    "lineEdit_16": "1",
    "lineEdit_17": "1",
    "lineEdit_18": "1",
    "lineEdit_19": "1",
    "lineEdit_20": "1",
    "lineEdit_21": "1",
    "lineEdit_22": "1",
    "lineEdit_23": "1",
    "lineEdit_24": "1",
    "lineEdit_25": "1",
    "lineEdit_26": "1",
    "lineEdit_27": "1",
    "lineEdit_28": "1"
}